README.md
main.py
pyproject.toml
video_mcp_server.egg-info/PKG-INFO
video_mcp_server.egg-info/SOURCES.txt
video_mcp_server.egg-info/dependency_links.txt
video_mcp_server.egg-info/requires.txt
video_mcp_server.egg-info/top_level.txt