Metadata-Version: 2.4
Name: video-mcp-server
Version: 0.1.0
Summary: Add your description here
Requires-Python: >=3.13
Requires-Dist: fastmcp>=2.9.0
